dash_tvlwc/Tvlwc.py
dash_tvlwc/__init__.py
dash_tvlwc/_imports_.py
dash_tvlwc/dash_tvlwc.min.js
dash_tvlwc/dash_tvlwc.min.js.map
dash_tvlwc/metadata.json
dash_tvlwc/package-info.json
dash_tvlwc/types.py
dash_tvlwc-0.1.1.dist-info/LICENSE
dash_tvlwc-0.1.1.dist-info/METADATA
dash_tvlwc-0.1.1.dist-info/WHEEL
dash_tvlwc-0.1.1.dist-info/top_level.txt
dash_tvlwc-0.1.1.dist-info/RECORD
