Metadata-Version: 2.1
Name: dash_tvlwc
Version: 0.1.1
Summary: Dash Component for Tradingview Lightweight Charts
Author: Kwan Yu, WU <wukwanyutyson@gmail.com>
License: MIT
Classifier: Framework :: Dash
License-File: LICENSE
